beckett/__init__.py
beckett/clients.py
beckett/constants.py
beckett/exceptions.py
beckett/resources.py
beckett-0.8.0.dist-info/DESCRIPTION.rst
beckett-0.8.0.dist-info/METADATA
beckett-0.8.0.dist-info/metadata.json
beckett-0.8.0.dist-info/RECORD
beckett-0.8.0.dist-info/top_level.txt
beckett-0.8.0.dist-info/WHEEL
