Metadata-Version: 1.1
Name: beckett
Version: 0.8.0
Summary: Hypermedia API Client Framework
Home-page: https://github.com/phalt/beckett
Author: Paul Hallett
Author-email: paulandrewhallett@gmail.com
License: ISCL
Keywords: beckett
Platform: UNKNOWN
Classifier: Development Status :: 3 - Alpha
Classifier: Intended Audience :: Developers
Classifier: License :: OSI Approved :: ISC License (ISCL)
Classifier: Natural Language :: English
Classifier: Programming Language :: Python :: 2
Classifier: Programming Language :: Python :: 2.6
Classifier: Programming Language :: Python :: 2.7
Classifier: Programming Language :: Python :: 3
Classifier: Programming Language :: Python :: 3.3
Classifier: Programming Language :: Python :: 3.4
Classifier: Programming Language :: Python :: 3.5
